{
  "case_title": "Barclays Bank Ltd v. W J Simms Son and Cooke (southern) Ltd and Another",
  "court": "Queen's Bench",
  "date": "24-4-1979",
  "year": "1979",
  "suit_number": "(1979)-3ALLE.R.522",
  "lex_citation": "LEX(1979)-3ALLE.R.522",
  "other_citations": [
    "2PLR/1979/8(QB)",
    "[1980]1QB677",
    "[1979]3ALLER522"
  ],
  "area_of_law": [
    "Banking and Finance Law",
    "Commercial Law",
    "Debtor and Creditor Law"
  ],
  "semantic_tags": [
    "Caselaw",
    "Legal Document",
    "Case"
  ],
  "judge": "Lord Robert Goff J",
  "representation": [
    "David Hunter Qc",
    "Peter Cresswell",
    "Barclays",
    "Edward Evans Lombe Qc",
    "Michael Crystal",
    "Durrant Piesse",
    "Harvey",
    "Ingram",
    "Leicester K Mydeen Esq",
    "Barrister"
  ],
  "doc_id": "e7531b8c-39a9-4838-b92e-59b515bd5a38",
  "doctype": "Case",
  "parties": [
    "Ys Bank Ltd",
    "W J Simms Son and Cooke (southern) Ltd and Another"
  ]
}