{
  "case_title": "Williams and Glyngçös Bank Ltd v. Boland and Another (hl) (2)",
  "court": "House of Lords",
  "date": "19-6-1980",
  "year": "1980",
  "suit_number": "",
  "lex_citation": "LEX(1980)-2ALLE.R.408",
  "other_citations": [
    "3PLR/1980/35(HL)",
    "[1981]AC487",
    "[1980]2ALLER408"
  ],
  "area_of_law": [
    "Real Estate and Property Law",
    "Words and Phrases",
    "Children and Women Law",
    "Debtor and Creditor",
    "Banking and Finance Law",
    "Family Law",
    "Estate Planning"
  ],
  "semantic_tags": [
    "Caselaw",
    "Legal Document",
    "Case",
    "High Profile Case"
  ],
  "judge": [
    "Lord Wilberforce",
    "Lord Salmon",
    "Viscount Dilhorne",
    "Lord Roskill",
    "Lord Scarman"
  ],
  "representation_appellant": [
    "Stephenson Harwood",
    "Jules",
    "Kanter"
  ],
  "representation_respondent": [
    "Hughmans",
    "Co",
    "Mary Rose Plummer"
  ],
  "doc_id": "b4ac2b07-cfb0-4260-aecd-a2c6916d8a05",
  "doctype": "Case",
  "parties": [
    "Williams and Glyn’s Bank Ltd",
    "Brown"
  ]
}