{
  "case_title": "Balogun v. National Bank of Nigeria Ltd",
  "court": "Supreme Court",
  "date": "9-3-1978",
  "year": "1978",
  "suit_number": "SC244/1976",
  "lex_citation": "LEX(1978)-SC244/1976",
  "other_citations": [
    "2PLR/1978/21(SC)",
    "(1978)ALLN.L.R63"
  ],
  "area_of_law": [
    "Banking and Finance Law",
    "Children and Women La",
    "Commercial Law",
    "Ethics",
    "Family Law",
    "Tort and Personal Injury",
    "Court",
    "Words and Phrase"
  ],
  "semantic_tags": [
    "Caselaw",
    "Legal Document",
    "Case",
    "High Profile Case"
  ],
  "judge": [
    "Darnley Arthur Alexander CJN",
    "Muhammed Bello JSC",
    "Chukwunwike Idigbe JSC"
  ],
  "representation": [
    "MR",
    "A. O.osipitan",
    "MR",
    "R. K. O. Oriade"
  ],
  "originating_court": [
    "",
    "High Court of Lagos State"
  ],
  "doc_id": "d3b613b3-c8de-4cb1-8152-a61fe9741f12",
  "doctype": "Case",
  "parties": [
    "Hirat Aderinsola Balogun",
    "National Bank of Nigeria Ltd"
  ]
}