{
  "case_title": "Bellinger (fc) v. Bellinger",
  "court": "House of Lords",
  "date": "10-4-2003",
  "year": "2003",
  "suit_number": "",
  "lex_citation": "",
  "other_citations": [
    "3PLR/2003/48(HL)",
    "[2003]UKHL21",
    "THEAPPELLATECOMMITTEECOMPRISED:",
    "LORDNICHOLLSOFBIRKENHEAD",
    "LORDHOPEOFCRAIGHEAD",
    "LORDHOBHOUSEOFWOODBOROUGH",
    "LORDSCOTTOFFOSCOTE",
    "LORDRODGEROFEARLSFERRY"
  ],
  "area_of_law": [
    "Healthcare and Law",
    "Jurisprudence",
    "International Law and Human Rights",
    "Children and Women Law",
    "Words and Phrases",
    "Family Law"
  ],
  "semantic_tags": [
    "Caselaw",
    "Legal Document",
    "Case",
    "High Profile Case"
  ],
  "judge": [
    "Lord Rodger of Earlsferry",
    "Lord Hope of Craighead",
    "Lord Hobhouse of Woodborough",
    "The Appellate Committee Comprised",
    "Lord Nicholls of Birkenhead",
    "Session 2002-03 on",
    "Bellinger",
    "Lord Scott of Foscote",
    "House of Lords",
    "Thursday 10 April",
    "Other Citations"
  ],
  "originating_court": [
    "Appeal From: [2001] Ewca Civ 1140"
  ],
  "doc_id": "f609ec2a-86ef-4c08-b5be-803fdb41d39a",
  "doctype": "Case",
  "parties": [
    "Bellinger (fc",
    "Bellinger"
  ]
}