{
  "case_title": "Udeakpu Eze v. Samuel Igiliegbe and Five Others",
  "court": "Court of Appeal",
  "date": "24-4-1952",
  "year": "1952",
  "suit_number": "(1952)14W.A.C.A.61AT62",
  "lex_citation": "LEX(1952)-14W.A.C.A.61",
  "other_citations": "2PLR/1952/18(WACA)",
  "area_of_law": [
    "Food",
    "Real Estate"
  ],
  "semantic_tags": [
    "Caselaw",
    "Legal Document",
    "Case"
  ],
  "judge": [
    "Maxime De Comarmond, Ag CJ",
    "James Henley Coussey J",
    "Stafford Foster-Sutton"
  ],
  "representation": [
    "G. C. M. Onyiuke",
    "C. D. Onyeama"
  ],
  "doc_id": "321a4838-536a-4688-acca-42cec3c7c747",
  "doctype": "Case",
  "parties": [
    "Udeakpu Eze",
    "Samuel Igiliegbe and Five Others"
  ]
}